{"_ts":[1542022931],"_r":{"breakdown":{"html":{"bytes":[40195],"requests":[20]},"js":{"bytes":[813908],"requests":[28]},"css":{"bytes":[135307],"requests":[3]},"image":{"bytes":[2056047],"requests":[122]},"flash":{"bytes":[0],"requests":[0]},"font":{"bytes":[125845],"requests":[5]},"video":{"bytes":[0],"requests":[0]},"other":{"bytes":[8143],"requests":[6]}},"date":[1542022931],"domElements":[2758],"domInteractive":[3400],"firstPaint":[2601.0000000024],"fullyLoaded":[15818],"id":["181112_M9_ff633a3ab53dcc8cabe2950220a97712"],"loadTime":[10207],"render":[4300],"SpeedIndex":[4393],"TTFB":[1324],"videoFrames":[[{"_i":"ms_000000.jpg","_t":0,"_vc":0},{"_i":"ms_004300.jpg","_t":4300,"_vc":98},{"_i":"ms_004800.jpg","_t":4800,"_vc":98},{"_i":"ms_004900.jpg","_t":4900,"_vc":98},{"_i":"ms_005200.jpg","_t":5200,"_vc":98},{"_i":"ms_005300.jpg","_t":5300,"_vc":98},{"_i":"ms_005500.jpg","_t":5500,"_vc":98},{"_i":"ms_006100.jpg","_t":6100,"_vc":98},{"_i":"ms_006200.jpg","_t":6200,"_vc":98},{"_i":"ms_006300.jpg","_t":6300,"_vc":98},{"_i":"ms_006800.jpg","_t":6800,"_vc":98},{"_i":"ms_006900.jpg","_t":6900,"_vc":98},{"_i":"ms_007000.jpg","_t":7000,"_vc":98},{"_i":"ms_007100.jpg","_t":7100,"_vc":98},{"_i":"ms_007200.jpg","_t":7200,"_vc":98},{"_i":"ms_007300.jpg","_t":7300,"_vc":98},{"_i":"ms_007400.jpg","_t":7400,"_vc":99},{"_i":"ms_007500.jpg","_t":7500,"_vc":99},{"_i":"ms_008100.jpg","_t":8100,"_vc":99},{"_i":"ms_008200.jpg","_t":8200,"_vc":99},{"_i":"ms_008500.jpg","_t":8500,"_vc":99},{"_i":"ms_008900.jpg","_t":8900,"_vc":99},{"_i":"ms_009200.jpg","_t":9200,"_vc":99},{"_i":"ms_009500.jpg","_t":9500,"_vc":99},{"_i":"ms_010300.jpg","_t":10300,"_vc":99},{"_i":"ms_010400.jpg","_t":10400,"_vc":100},{"_i":"ms_010500.jpg","_t":10500,"_vc":100},{"_i":"ms_010600.jpg","_t":10600,"_vc":99},{"_i":"ms_010700.jpg","_t":10700,"_vc":100},{"_i":"ms_010801.jpg","_t":10801,"_vc":99},{"_i":"ms_010900.jpg","_t":10900,"_vc":100}]],"visualComplete":[10400],"lighthouse":[27],"pagespeed":[45]}}